{
    "Endangering National Security": {
        "num_samples": 15,
        "max_ppl_A_direct": 20.201,
        "min_ppl_A_direct": 13.825,
        "mean_ppl_A_direct": 16.05,
        "std_ppl_A_direct": 1.703,
        "max_ppl_A_condition": 9.792,
        "min_ppl_A_condition": 8.049,
        "mean_ppl_A_condition": 8.643,
        "std_ppl_A_condition": 0.498,
        "max_ifd_ppl": 0.595,
        "min_ifd_ppl": 0.46,
        "mean_ifd_ppl": 0.542,
        "std_ifd_ppl": 0.042
    },
    "Insulting Behavior": {
        "num_samples": 41,
        "max_ppl_A_direct": 21.273,
        "min_ppl_A_direct": 13.566,
        "mean_ppl_A_direct": 17.057,
        "std_ppl_A_direct": 1.948,
        "max_ppl_A_condition": 9.796,
        "min_ppl_A_condition": 8.004,
        "mean_ppl_A_condition": 8.917,
        "std_ppl_A_condition": 0.583,
        "max_ifd_ppl": 0.596,
        "min_ifd_ppl": 0.405,
        "mean_ifd_ppl": 0.528,
        "std_ifd_ppl": 0.055
    },
    "Discriminatory Behavior": {
        "num_samples": 22,
        "max_ppl_A_direct": 23.347,
        "min_ppl_A_direct": 14.031,
        "mean_ppl_A_direct": 16.861,
        "std_ppl_A_direct": 2.27,
        "max_ppl_A_condition": 9.952,
        "min_ppl_A_condition": 8.033,
        "mean_ppl_A_condition": 8.958,
        "std_ppl_A_condition": 0.589,
        "max_ifd_ppl": 0.591,
        "min_ifd_ppl": 0.426,
        "mean_ifd_ppl": 0.537,
        "std_ifd_ppl": 0.046
    },
    "Endangering Public Health": {
        "num_samples": 9,
        "max_ppl_A_direct": 19.525,
        "min_ppl_A_direct": 14.595,
        "mean_ppl_A_direct": 16.067,
        "std_ppl_A_direct": 1.415,
        "max_ppl_A_condition": 9.937,
        "min_ppl_A_condition": 8.049,
        "mean_ppl_A_condition": 9.039,
        "std_ppl_A_condition": 0.549,
        "max_ifd_ppl": 0.598,
        "min_ifd_ppl": 0.475,
        "mean_ifd_ppl": 0.565,
        "std_ifd_ppl": 0.036
    },
    "Copyright Issues": {
        "num_samples": 5,
        "max_ppl_A_direct": 18.898,
        "min_ppl_A_direct": 13.449,
        "mean_ppl_A_direct": 16.244,
        "std_ppl_A_direct": 1.738,
        "max_ppl_A_condition": 9.702,
        "min_ppl_A_condition": 8.061,
        "mean_ppl_A_condition": 8.987,
        "std_ppl_A_condition": 0.619,
        "max_ifd_ppl": 0.599,
        "min_ifd_ppl": 0.475,
        "mean_ifd_ppl": 0.557,
        "std_ifd_ppl": 0.046
    },
    "Violence": {
        "num_samples": 34,
        "max_ppl_A_direct": 23.915,
        "min_ppl_A_direct": 13.561,
        "mean_ppl_A_direct": 17.134,
        "std_ppl_A_direct": 2.687,
        "max_ppl_A_condition": 9.913,
        "min_ppl_A_condition": 8.017,
        "mean_ppl_A_condition": 8.75,
        "std_ppl_A_condition": 0.542,
        "max_ifd_ppl": 0.6,
        "min_ifd_ppl": 0.401,
        "mean_ifd_ppl": 0.52,
        "std_ifd_ppl": 0.064
    },
    "Drugs": {
        "num_samples": 10,
        "max_ppl_A_direct": 19.131,
        "min_ppl_A_direct": 13.512,
        "mean_ppl_A_direct": 16.065,
        "std_ppl_A_direct": 1.796,
        "max_ppl_A_condition": 9.669,
        "min_ppl_A_condition": 8.037,
        "mean_ppl_A_condition": 8.513,
        "std_ppl_A_condition": 0.545,
        "max_ifd_ppl": 0.598,
        "min_ifd_ppl": 0.42,
        "mean_ifd_ppl": 0.535,
        "std_ifd_ppl": 0.055
    },
    "Privacy Violation": {
        "num_samples": 62,
        "max_ppl_A_direct": 23.593,
        "min_ppl_A_direct": 13.512,
        "mean_ppl_A_direct": 16.833,
        "std_ppl_A_direct": 2.217,
        "max_ppl_A_condition": 9.954,
        "min_ppl_A_condition": 8.055,
        "mean_ppl_A_condition": 8.818,
        "std_ppl_A_condition": 0.505,
        "max_ifd_ppl": 0.599,
        "min_ifd_ppl": 0.403,
        "mean_ifd_ppl": 0.53,
        "std_ifd_ppl": 0.054
    },
    "Economic Crime": {
        "num_samples": 60,
        "max_ppl_A_direct": 21.941,
        "min_ppl_A_direct": 13.736,
        "mean_ppl_A_direct": 17.102,
        "std_ppl_A_direct": 1.878,
        "max_ppl_A_condition": 9.954,
        "min_ppl_A_condition": 8.004,
        "mean_ppl_A_condition": 8.848,
        "std_ppl_A_condition": 0.516,
        "max_ifd_ppl": 0.599,
        "min_ifd_ppl": 0.413,
        "mean_ifd_ppl": 0.522,
        "std_ifd_ppl": 0.05
    },
    "Mental Manipulation": {
        "num_samples": 37,
        "max_ppl_A_direct": 24.598,
        "min_ppl_A_direct": 13.561,
        "mean_ppl_A_direct": 16.497,
        "std_ppl_A_direct": 2.283,
        "max_ppl_A_condition": 9.937,
        "min_ppl_A_condition": 8.076,
        "mean_ppl_A_condition": 8.802,
        "std_ppl_A_condition": 0.563,
        "max_ifd_ppl": 0.6,
        "min_ifd_ppl": 0.401,
        "mean_ifd_ppl": 0.54,
        "std_ifd_ppl": 0.056
    },
    "Human Trafficking": {
        "num_samples": 15,
        "max_ppl_A_direct": 24.598,
        "min_ppl_A_direct": 13.976,
        "mean_ppl_A_direct": 16.56,
        "std_ppl_A_direct": 2.428,
        "max_ppl_A_condition": 9.868,
        "min_ppl_A_condition": 8.037,
        "mean_ppl_A_condition": 8.81,
        "std_ppl_A_condition": 0.516,
        "max_ifd_ppl": 0.595,
        "min_ifd_ppl": 0.401,
        "mean_ifd_ppl": 0.538,
        "std_ifd_ppl": 0.049
    },
    "Physical Harm": {
        "num_samples": 34,
        "max_ppl_A_direct": 23.915,
        "min_ppl_A_direct": 13.736,
        "mean_ppl_A_direct": 17.111,
        "std_ppl_A_direct": 2.281,
        "max_ppl_A_condition": 9.992,
        "min_ppl_A_condition": 8.027,
        "mean_ppl_A_condition": 8.946,
        "std_ppl_A_condition": 0.602,
        "max_ifd_ppl": 0.599,
        "min_ifd_ppl": 0.412,
        "mean_ifd_ppl": 0.529,
        "std_ifd_ppl": 0.054
    },
    "Sexual Content": {
        "num_samples": 11,
        "max_ppl_A_direct": 19.544,
        "min_ppl_A_direct": 13.742,
        "mean_ppl_A_direct": 16.788,
        "std_ppl_A_direct": 1.967,
        "max_ppl_A_condition": 9.704,
        "min_ppl_A_condition": 8.181,
        "mean_ppl_A_condition": 8.895,
        "std_ppl_A_condition": 0.564,
        "max_ifd_ppl": 0.595,
        "min_ifd_ppl": 0.485,
        "mean_ifd_ppl": 0.534,
        "std_ifd_ppl": 0.039
    },
    "Cybercrime": {
        "num_samples": 59,
        "max_ppl_A_direct": 20.841,
        "min_ppl_A_direct": 13.512,
        "mean_ppl_A_direct": 16.354,
        "std_ppl_A_direct": 1.774,
        "max_ppl_A_condition": 9.947,
        "min_ppl_A_condition": 8.004,
        "mean_ppl_A_condition": 8.816,
        "std_ppl_A_condition": 0.514,
        "max_ifd_ppl": 0.598,
        "min_ifd_ppl": 0.401,
        "mean_ifd_ppl": 0.544,
        "std_ifd_ppl": 0.05
    },
    "Disrupting Public Order": {
        "num_samples": 17,
        "max_ppl_A_direct": 20.533,
        "min_ppl_A_direct": 13.928,
        "mean_ppl_A_direct": 16.052,
        "std_ppl_A_direct": 1.773,
        "max_ppl_A_condition": 9.895,
        "min_ppl_A_condition": 8.038,
        "mean_ppl_A_condition": 8.79,
        "std_ppl_A_condition": 0.499,
        "max_ifd_ppl": 0.6,
        "min_ifd_ppl": 0.432,
        "mean_ifd_ppl": 0.552,
        "std_ifd_ppl": 0.045
    },
    "Environmental Damage": {
        "num_samples": 10,
        "max_ppl_A_direct": 17.487,
        "min_ppl_A_direct": 14.092,
        "mean_ppl_A_direct": 15.279,
        "std_ppl_A_direct": 1.048,
        "max_ppl_A_condition": 9.992,
        "min_ppl_A_condition": 8.049,
        "mean_ppl_A_condition": 8.71,
        "std_ppl_A_condition": 0.586,
        "max_ifd_ppl": 0.6,
        "min_ifd_ppl": 0.542,
        "mean_ifd_ppl": 0.57,
        "std_ifd_ppl": 0.018
    },
    "Psychological Harm": {
        "num_samples": 34,
        "max_ppl_A_direct": 19.292,
        "min_ppl_A_direct": 13.561,
        "mean_ppl_A_direct": 16.098,
        "std_ppl_A_direct": 1.429,
        "max_ppl_A_condition": 9.937,
        "min_ppl_A_condition": 8.129,
        "mean_ppl_A_condition": 8.958,
        "std_ppl_A_condition": 0.573,
        "max_ifd_ppl": 0.599,
        "min_ifd_ppl": 0.483,
        "mean_ifd_ppl": 0.558,
        "std_ifd_ppl": 0.031
    },
    "White-Collar Crime": {
        "num_samples": 25,
        "max_ppl_A_direct": 22.957,
        "min_ppl_A_direct": 14.299,
        "mean_ppl_A_direct": 16.69,
        "std_ppl_A_direct": 2.145,
        "max_ppl_A_condition": 9.704,
        "min_ppl_A_condition": 8.053,
        "mean_ppl_A_condition": 8.762,
        "std_ppl_A_condition": 0.409,
        "max_ifd_ppl": 0.599,
        "min_ifd_ppl": 0.413,
        "mean_ifd_ppl": 0.531,
        "std_ifd_ppl": 0.055
    },
    "Animal Abuse": {
        "num_samples": 6,
        "max_ppl_A_direct": 21.085,
        "min_ppl_A_direct": 15.144,
        "mean_ppl_A_direct": 17.861,
        "std_ppl_A_direct": 1.999,
        "max_ppl_A_condition": 9.876,
        "min_ppl_A_condition": 8.477,
        "mean_ppl_A_condition": 9.396,
        "std_ppl_A_condition": 0.494,
        "max_ifd_ppl": 0.589,
        "min_ifd_ppl": 0.464,
        "mean_ifd_ppl": 0.53,
        "std_ifd_ppl": 0.042
    },
    "summary": {
        "num_samples": 256,
        "num_nans": 0,
        "num_categories": 19,
        "max_ppl_A_direct": 24.598,
        "min_ppl_A_direct": 13.449,
        "mean_ppl_A_direct": 16.906,
        "std_ppl_A_direct": 2.201,
        "max_ppl_A_condition": 9.992,
        "min_ppl_A_condition": 8.004,
        "mean_ppl_A_condition": 8.87,
        "std_ppl_A_condition": 0.553,
        "max_ifd_ppl": 0.6,
        "min_ifd_ppl": 0.401,
        "mean_ifd_ppl": 0.531,
        "std_ifd_ppl": 0.054
    }
}